LICENSE.txt
MANIFEST.in
edkit-server
setup.py
edkit_server/__init__.py
edkit_server.egg-info/PKG-INFO
edkit_server.egg-info/SOURCES.txt
edkit_server.egg-info/dependency_links.txt
edkit_server.egg-info/requires.txt
edkit_server.egg-info/top_level.txt
edkit_server/.crossbar/config.json
edkit_server/edleak/__init__.py
edkit_server/edleak/classifier.py
edkit_server/edleak/edleak-class.pickle
edkit_server/edleak/features.py
edkit_server/wamp/__init__.py
edkit_server/wamp/edleak.py
edkit_server/web/edleak/.DS_Store
edkit_server/web/edleak/favicon.ico
edkit_server/web/edleak/index.html
edkit_server/web/edleak/index.js
edkit_server/web/edleak/lib/autobahn.min.jgz
edkit_server/web/edleak/lib/highcharts.js
edkit_server/web/edleak/lib/jquery-3.1.1.min.js
edkit_server/web/edleak/lib/protovis-r3.2.js
edkit_server/web/edleak/lib/semantic.min.js
edkit_server/web/edleak/style/.DS_Store
edkit_server/web/edleak/style/default.css
edkit_server/web/edleak/style/download.png
edkit_server/web/edleak/style/upload.png
edkit_server/web/edleak/style/semantic/semantic.min.css
edkit_server/web/edleak/style/semantic/themes/default/assets/fonts/icons.eot
edkit_server/web/edleak/style/semantic/themes/default/assets/fonts/icons.svg
edkit_server/web/edleak/style/semantic/themes/default/assets/fonts/icons.ttf
edkit_server/web/edleak/style/semantic/themes/default/assets/fonts/icons.woff
edkit_server/web/edleak/style/semantic/themes/default/assets/fonts/icons.woff2
edkit_server/web/edleak/style/semantic/themes/default/assets/images/flags.png