Metadata-Version: 1.1
Name: edkit-server
Version: 0.3.1
Summary: edkit server package for local usage
Home-page: https://github.com/edkit/edkit-server
Author: Romain Picard
Author-email: romain.picard@oakbits.com
License: MIT
Platform: any
Classifier: Development Status :: 3 - Alpha
Classifier: License :: OSI Approved :: MIT License
Classifier: Intended Audience :: Developers
Classifier: Programming Language :: Python :: 3
Classifier: Topic :: Software Development :: Debuggers
